{
  "project_info": {
    "project_number": "533569762185",
    "project_id": "kupa-84b98",
    "storage_bucket": "kupa-84b98.appspot.com"
  },
  "client": [
    {
      "client_info": {
        "mobilesdk_app_id": "1:533569762185:android:6cd3833b6269813e9de758",
        "android_client_info": {
          "package_name": "com.example.kupa"
        }
      },
      "oauth_client": [
        {
          "client_id": "533569762185-gp32cgk73m0ra6k402pcsem3166vm8kv.apps.googleusercontent.com",
          "client_type": 3
        }
      ],
      "api_key": [
        {
          "current_key": "AIzaSyAYM1z36DD03UADgA6AIW-ZKvUURFC4NF4"
        }
      ],
      "services": {
        "appinvite_service": {
          "other_platform_oauth_client": [
            {
              "client_id": "533569762185-gp32cgk73m0ra6k402pcsem3166vm8kv.apps.googleusercontent.com",
              "client_type": 3
            }
          ]
        }
      }
    }
  ],
  "configuration_version": "1"
}